phddsf22m001scraper/__init__.py
phddsf22m001scraper-0.1.dist-info/LICENSE.txt
phddsf22m001scraper-0.1.dist-info/METADATA
phddsf22m001scraper-0.1.dist-info/WHEEL
phddsf22m001scraper-0.1.dist-info/top_level.txt
phddsf22m001scraper-0.1.dist-info/RECORD
