Metadata-Version: 2.1
Name: phddsf22m001scraper
Version: 0.1
Summary: A web scraper that returns parsed response for a given taget
Author: Muhammad Husnain
Author-email: m.husnain8721@gmail.com
Classifier: Programming Language :: Python :: 3
Classifier: License :: OSI Approved :: MIT License
Classifier: Operating System :: OS Independent
License-File: LICENSE.txt
Requires-Dist: requests
Requires-Dist: beautifulsoup4
